.bumpversion.cfg
.cookiecutterrc
.coveragerc
.editorconfig
.travis.yml
AUTHORS.rst
CHANGELOG.rst
CONTRIBUTING.rst
LICENSE
MANIFEST.in
README.rst
requirements.txt
setup.cfg
setup.py
tox.ini
ci/bootstrap.py
ci/templates/.travis.yml
docs/authors.rst
docs/changelog.rst
docs/conf.py
docs/contributing.rst
docs/index.rst
docs/installation.rst
docs/readme.rst
docs/requirements.txt
docs/spelling_wordlist.txt
docs/usage.rst
docs/reference/index.rst
docs/reference/pylendingclub.rst
src/pylendingclub/__init__.py
src/pylendingclub/__main__.py
src/pylendingclub/cli.py
src/pylendingclub/config.py
src/pylendingclub/errors.py
src/pylendingclub.egg-info/PKG-INFO
src/pylendingclub.egg-info/SOURCES.txt
src/pylendingclub.egg-info/dependency_links.txt
src/pylendingclub.egg-info/entry_points.txt
src/pylendingclub.egg-info/not-zip-safe
src/pylendingclub.egg-info/top_level.txt
src/pylendingclub/autoinvestor/__init__.py
src/pylendingclub/autoinvestor/autoinvestor.py
src/pylendingclub/wrapper/__init__.py
src/pylendingclub/wrapper/account.py
src/pylendingclub/wrapper/base.py
src/pylendingclub/wrapper/funds.py
src/pylendingclub/wrapper/loan.py
src/pylendingclub/wrapper/order.py
src/pylendingclub/wrapper/request.py
src/pylendingclub/wrapper/resource.py
src/pylendingclub/wrapper/session.py
tests/test_pylendingclub.py
tests/wrapper/wrapper_test.py