Metadata-Version: 1.1
Name: pylendingclub
Version: 3.0.2
Summary: A python package for automating the LendingClub API.
Home-page: https://github.com/bbarney213/PyLendingClub
Author: Brandon Dean Barney
Author-email: brandon.barney213@yahoo.com
License: BSD 3-Clause License
Keywords: python,investing,finance,api-wrapper,lending-club,lending-club-api,p2p-investing
Platform: UNKNOWN
Classifier: Development Status :: 5 - Production/Stable
Classifier: Intended Audience :: Developers
Classifier: License :: OSI Approved :: BSD License
Classifier: Programming Language :: Python
Classifier: Programming Language :: Python :: 3
Classifier: Programming Language :: Python :: 3.4
Classifier: Programming Language :: Python :: 3.5
Classifier: Programming Language :: Python :: 3.6
Classifier: Programming Language :: Python :: 3.7
